BeginnersbookServletJiaochengChuyiFix1/README.md
BeginnersbookServletJiaochengChuyiFix1/__init__.py
BeginnersbookServletJiaochengChuyiFix1/__main__.py
BeginnersbookServletJiaochengChuyiFix1/file.epub
BeginnersbookServletJiaochengChuyiFix1/index.html
BeginnersbookServletJiaochengChuyiFix1/css/__init__.py
BeginnersbookServletJiaochengChuyiFix1/css/annotations.css
BeginnersbookServletJiaochengChuyiFix1/css/main.css
BeginnersbookServletJiaochengChuyiFix1/css/normalize.css
BeginnersbookServletJiaochengChuyiFix1/css/popup.css
BeginnersbookServletJiaochengChuyiFix1/font/__init__.py
BeginnersbookServletJiaochengChuyiFix1/font/fontello.eot
BeginnersbookServletJiaochengChuyiFix1/font/fontello.svg
BeginnersbookServletJiaochengChuyiFix1/font/fontello.ttf
BeginnersbookServletJiaochengChuyiFix1/font/fontello.woff
BeginnersbookServletJiaochengChuyiFix1/img/__init__.py
BeginnersbookServletJiaochengChuyiFix1/img/annotator-glyph-sprite.png
BeginnersbookServletJiaochengChuyiFix1/img/annotator-icon-sprite.png
BeginnersbookServletJiaochengChuyiFix1/img/apple-touch-icon.png
BeginnersbookServletJiaochengChuyiFix1/img/cancelfullscreen.png
BeginnersbookServletJiaochengChuyiFix1/img/close.png
BeginnersbookServletJiaochengChuyiFix1/img/fullscreen.png
BeginnersbookServletJiaochengChuyiFix1/img/loader.gif
BeginnersbookServletJiaochengChuyiFix1/img/menu-icon.png
BeginnersbookServletJiaochengChuyiFix1/img/save.png
BeginnersbookServletJiaochengChuyiFix1/img/saved.png
BeginnersbookServletJiaochengChuyiFix1/img/settings-s.png
BeginnersbookServletJiaochengChuyiFix1/img/settings.png
BeginnersbookServletJiaochengChuyiFix1/img/star.png
BeginnersbookServletJiaochengChuyiFix1/js/__init__.py
BeginnersbookServletJiaochengChuyiFix1/js/epub.js
BeginnersbookServletJiaochengChuyiFix1/js/epub.min.js
BeginnersbookServletJiaochengChuyiFix1/js/epub.min.map
BeginnersbookServletJiaochengChuyiFix1/js/hooks.min.js
BeginnersbookServletJiaochengChuyiFix1/js/hooks.min.map
beginnersbook_servlet_jiaocheng_chuyi_fix1-2025.3.24.1.dist-info/METADATA
beginnersbook_servlet_jiaocheng_chuyi_fix1-2025.3.24.1.dist-info/WHEEL
beginnersbook_servlet_jiaocheng_chuyi_fix1-2025.3.24.1.dist-info/entry_points.txt
beginnersbook_servlet_jiaocheng_chuyi_fix1-2025.3.24.1.dist-info/top_level.txt
beginnersbook_servlet_jiaocheng_chuyi_fix1-2025.3.24.1.dist-info/RECORD
